{"cameraMode":{"drawMode":0,"name":"Shaded","section":"Shading Mode"},"sceneLighting":true,"audioPlay":false,"sceneViewState":{"m_AlwaysRefresh":false,"showFog":true,"showSkybox":true,"showFlares":true,"showImageEffects":true,"showParticleSystems":true,"showVisualEffectGraphs":true,"m_FxEnabled":true},"in2DMode":false,"pivot":{"x":537.9189453125,"y":228.074462890625,"z":-1213.13232421875},"rotation":{"x":-0.043791234493255618,"y":-0.014388247393071652,"z":0.0006306946743279696,"w":-0.9989370703697205},"size":3.0672426223754885,"orthographic":false}